odoo/addons/sale_project_copy_tasks/README.rst
odoo/addons/sale_project_copy_tasks/__init__.py
odoo/addons/sale_project_copy_tasks/__manifest__.py
odoo/addons/sale_project_copy_tasks/i18n/es.po
odoo/addons/sale_project_copy_tasks/i18n/it.po
odoo/addons/sale_project_copy_tasks/i18n/sale_project_copy_tasks.pot
odoo/addons/sale_project_copy_tasks/i18n/sale_project_service_tracking_copy_tasks.pot
odoo/addons/sale_project_copy_tasks/models/__init__.py
odoo/addons/sale_project_copy_tasks/models/product_template.py
odoo/addons/sale_project_copy_tasks/models/sale_order.py
odoo/addons/sale_project_copy_tasks/models/sale_order_line.py
odoo/addons/sale_project_copy_tasks/readme/CONTEXT.md
odoo/addons/sale_project_copy_tasks/readme/CONTRIBUTORS.md
odoo/addons/sale_project_copy_tasks/readme/DESCRIPTION.md
odoo/addons/sale_project_copy_tasks/readme/USAGE.md
odoo/addons/sale_project_copy_tasks/static/description/icon.png
odoo/addons/sale_project_copy_tasks/static/description/index.html
odoo/addons/sale_project_copy_tasks/tests/__init__.py
odoo/addons/sale_project_copy_tasks/tests/test_copy_task.py
odoo/addons/sale_project_copy_tasks/views/product_template_views.xml
odoo/addons/sale_project_copy_tasks/views/sale_order_views.xml
odoo_addon_sale_project_copy_tasks-18.0.1.0.0.2.dist-info/METADATA
odoo_addon_sale_project_copy_tasks-18.0.1.0.0.2.dist-info/WHEEL
odoo_addon_sale_project_copy_tasks-18.0.1.0.0.2.dist-info/top_level.txt
odoo_addon_sale_project_copy_tasks-18.0.1.0.0.2.dist-info/RECORD
